find_files/__init__.py
find_files/file.py
find_files-0.0.1.dist-info/LICENSE.txt
find_files-0.0.1.dist-info/METADATA
find_files-0.0.1.dist-info/WHEEL
find_files-0.0.1.dist-info/top_level.txt
find_files-0.0.1.dist-info/RECORD
