Metadata-Version: 2.1
Name: find-files
Version: 0.0.1
Summary: To find the file by using name and extension for your given directory
Home-page: https://github.com/elaa0505/find_files
Author: Elango SK
Author-email: elango111000@gmail.com
License: UNKNOWN
Keywords: Find files,find files using pattern
Platform: UNKNOWN
